discord/ext/wizards/__init__.py
discord/ext/wizards/action.py
discord/ext/wizards/constants.py
discord/ext/wizards/step.py
discord/ext/wizards/stopreason.py
discord/ext/wizards/wizard.py
discord_ext_wizards-0.3.0.dist-info/LICENSE
discord_ext_wizards-0.3.0.dist-info/METADATA
discord_ext_wizards-0.3.0.dist-info/WHEEL
discord_ext_wizards-0.3.0.dist-info/top_level.txt
discord_ext_wizards-0.3.0.dist-info/RECORD
