Metadata-Version: 2.1
Name: discord-ext-wizards
Version: 0.3.0
Summary: A module for making setup wizards easily.
Home-page: https://github.com/CircuitsBots/discord-ext-wizards
Author: Circuit
License: MIT
Platform: UNKNOWN
Requires-Python: >=3.5.3
Requires-Dist: discord.py (>=1.2.5)
